.gitignore
LICENSE
README.md
pyproject.toml
uv.lock
.github/workflows/python-package.yml
.github/workflows/python-publish.yml
.github/workflows/run-tests.yml
.vscode/launch.json
examples/example_1.py
examples/example_2.py
examples/example_3.py
memodisk/__init__.py
memodisk/_version.py
memodisk/development.md
memodisk/memodisk.py
memodisk/py.typed
memodisk.egg-info/PKG-INFO
memodisk.egg-info/SOURCES.txt
memodisk.egg-info/dependency_links.txt
memodisk.egg-info/requires.txt
memodisk.egg-info/top_level.txt
tests/code_test_code_dep_1_a.py
tests/code_test_code_dep_1_b.py
tests/code_test_code_dep_numba_a.py
tests/code_test_code_dep_numba_b.py
tests/non_pure_functions.py
tests/test_class.py
tests/test_closure.py
tests/test_code_dependency.py
tests/test_data_dependency_change.py
tests/test_data_dependency_change_monkey_patch.py
tests/test_decorator.py
tests/test_dependency_inheritance.py
tests/test_dependency_inheritance_a.py
tests/test_dependency_inheritance_b.py
tests/test_internals.py
tests/test_memoize_random_state.py
tests/test_method_dependency.py
tests/test_nested_memoize.py
tests/test_non_pure_functions.py
tests/test_numba.py
tests/__memodisk__/__main__.f2_48fdc14256d5fb8d_dependencies.json
tests/__memodisk__/__main__.f2_48fdc14256d5fb8d_result.pkl
tests/__memodisk__/__main__.f3_4a6f12b45303cb21_dependencies.json
tests/__memodisk__/__main__.f3_4a6f12b45303cb21_result.pkl
tests/__memodisk__/__main__.fun_a_a18bf514f8e6e6e6_dependencies.json
tests/__memodisk__/__main__.fun_a_a18bf514f8e6e6e6_result.pkl
tests/__memodisk__/__main__.fun_b_1eba499228544c31_dependencies.json
tests/__memodisk__/__main__.fun_b_1eba499228544c31_result.pkl