Metadata-Version: 2.4
Name: memodisk
Version: 0.0.6.dev0
Summary: A python module to memoize function results on disk with python code and data dependencies tracking
Author-email: Martin de La Gorce <martin.delagorce@gmail.com>
Maintainer-email: Martin de La Gorce <martin.delagorce@gmail.com>
License: MIT License
Project-URL: Homepage, https://github.com/martinResearch/memodisk
Project-URL: Repository, https://github.com/martinResearch/memodisk
Keywords: memoization,caching,persistent,dependency-tracking,disk-cache,decorator
Classifier: Development Status :: 3 - Alpha
Classifier: Intended Audience :: Developers
Classifier: Intended Audience :: Science/Research
Classifier: License :: OSI Approved :: MIT License
Classifier: Operating System :: OS Independent
Classifier: Programming Language :: Python :: 3.10
Requires-Python: ==3.10.*
License-File: LICENSE
Requires-Dist: typing-extensions>=4.0.0
Provides-Extra: dev
Requires-Dist: pytest>=6.0; extra == "dev"
Requires-Dist: pytest-cov; extra == "dev"
Requires-Dist: ruff>=0.1.0; extra == "dev"
Requires-Dist: mypy; extra == "dev"
Requires-Dist: pre-commit; extra == "dev"
Requires-Dist: build; extra == "dev"
Requires-Dist: twine; extra == "dev"
Provides-Extra: test
Requires-Dist: pytest>=6.0; extra == "test"
Requires-Dist: pytest-cov; extra == "test"
Requires-Dist: numpy>1.24.4; extra == "test"
Requires-Dist: numba>=0.61; extra == "test"
Requires-Dist: opencv-python; extra == "test"
Dynamic: license-file
